bagel_tushare-3.0.0.dist-info/licenses/LICENSE
bageltushare/__init__.py
bageltushare/database.py
bageltushare/download.py
bageltushare/tushare_api.py
bageltushare/queries/__init__.py
bageltushare/queries/for_download.py
bagel_tushare-3.0.0.dist-info/METADATA
bagel_tushare-3.0.0.dist-info/WHEEL
bagel_tushare-3.0.0.dist-info/top_level.txt
bagel_tushare-3.0.0.dist-info/RECORD
