Metadata-Version: 2.4
Name: bagel-tushare
Version: 3.0.0
Summary: A Python wrapper for Tushare, a Chinese financial data provider. The project provides a simple and easy-to-use automation tool for **downloading** financial data from Tushare, and **storing** the data in a local mysql database.
Author-email: Yanzhong Huang <eric.yanzhong.huang@gmail.com>
Project-URL: Homepage, https://github.com/bagelquant/bagel-tushare
Project-URL: Issues, https://github.com/bagelquant/bagel-tushare/issues
Classifier: Programming Language :: Python :: 3
Classifier: License :: OSI Approved :: MIT License
Classifier: Operating System :: OS Independent
Requires-Python: >=3.10
License-File: LICENSE
Requires-Dist: pandas>=2.2.0
Requires-Dist: tushare>=1.4.0
Requires-Dist: pymysql>=1.1.1
Requires-Dist: sqlalchemy>=2.0.0
Requires-Dist: cryptography>=43.0.0
Dynamic: license-file
